src/__init__.py
src/fruit.py
fruity-0.1.0.dist-info/LICENSE.txt
fruity-0.1.0.dist-info/METADATA
fruity-0.1.0.dist-info/WHEEL
fruity-0.1.0.dist-info/top_level.txt
fruity-0.1.0.dist-info/RECORD
